<PAMDataset>
  <PAMRasterBand band="1">
    <Histograms>
      <HistItem>
        <HistMin>-93,49911190053285</HistMin>
        <HistMax>469,4991119005329</HistMax>
        <BucketCount>563</BucketCount>
        <IncludeOutOfRange>0</IncludeOutOfRange>
        <Approximate>1</Approximate>
        <HistCounts>3|39|32|11|9|11|9|8|7|43|33|39|25|87|90|72|51|42|32|73|62|129|111|106|84|74|76|94|132|121|96|60|48|46|37|62|81|68|71|62|48|39|41|45|46|57|52|48|42|38|30|34|34|64|42|38|33|38|35|44|49|49|90|55|53|82|46|48|45|47|44|43|48|60|88|124|64|59|40|51|45|48|40|97|95|95|101|83|103|103|82|79|101|153|116|125|117|112|124|111|74|83|58|92|110|114|75|139|171|151|135|135|134|161|137|141|134|206|173|132|150|177|212|237|211|194|218|233|219|254|183|203|194|191|187|182|201|215|156|169|201|172|173|149|138|104|134|132|142|118|86|110|119|123|105|118|123|146|153|136|140|169|164|160|148|116|169|130|137|141|163|144|140|138|144|157|136|177|152|149|141|135|167|204|184|193|183|208|202|169|187|193|230|251|237|211|203|206|236|277|236|254|248|241|260|256|282|287|284|286|353|380|424|416|388|341|344|309|370|349|361|324|335|312|287|346|305|292|337|356|277|297|344|348|389|354|385|297|361|347|351|359|350|325|334|338|371|352|404|423|384|449|393|376|362|386|372|403|498|424|366|376|393|356|424|489|471|430|402|395|386|325|358|354|386|476|468|405|425|494|535|586|663|638|609|608|657|650|548|600|596|575|562|578|602|524|573|608|624|566|546|582|587|552|575|653|648|595|736|715|667|638|601|625|491|453|513|462|503|487|466|477|444|520|434|429|592|547|546|505|476|514|521|466|500|468|447|467|433|457|495|455|460|513|484|565|600|632|624|467|499|488|526|495|491|514|508|468|531|517|509|501|514|518|510|500|512|480|460|471|506|483|507|562|497|504|471|435|507|526|486|512|621|644|652|608|635|733|720|689|633|691|704|686|653|664|611|564|618|661|694|655|710|653|621|551|614|594|599|693|574|614|713|605|573|490|575|419|376|350|386|362|320|289|278|282|274|239|232|259|290|232|220|270|222|224|235|212|200|215|171|196|201|180|149|148|168|161|147|157|205|216|216|183|188|167|199|173|163|144|139|135|150|157|143|158|161|187|188|185|205|178|154|191|160|169|206|241|201|214|232|238|241|214|208|203|203|187|183|188|174|171|175|184|211|174|200|292|334|210|224|185|160|225|208|249|221|215|267|210|202|161|171|173|125|101|104|84|89|56|54|60|63|80|80|39|37|40|28|49|42|51|63|34|24|21|16|32|21|28|21|21|18|20|20|37|22|30|37|23|14|16|16|14|13|16|17|20|18|6|3|4|1</HistCounts>
      </HistItem>
    </Histograms>
  </PAMRasterBand>
</PAMDataset>
